{
    "2023-10-01": {
        "total": 45,
        "apps": {
            "TikTok": 20,
            "Instagram": 25
        }
    },
    "2023-10-02": {
        "total": 120,
        "apps": {
            "YouTube Shorts": 90,
            "Twitter": 30
        }
    },
    "2023-10-03": {
        "total": 30,
        "apps": {
            "Instagram": 30
        }
    },
    "2023-10-04": {
        "total": 60,
        "apps": {
            "TikTok": 60
        }
    },
    "2023-10-05": {
        "total": 15,
        "apps": {
            "Twitter": 15
        }
    },
    "2023-10-06": {
        "total": 90,
        "apps": {
            "YouTube Shorts": 45,
            "TikTok": 45
        }
    },
    "2023-10-07": {
        "total": 200,
        "apps": {
            "TikTok": 120,
            "Instagram": 80
        }
    },
    "2023-10-08": {
        "total": 5,
        "apps": {
            "Twitter": 5
        }
    },
    "2023-10-09": {
        "total": 45,
        "apps": {
            "Instagram": 45
        }
    },
    "2023-10-10": {
        "total": 110,
        "apps": {
            "YouTube Shorts": 110
        }
    }
}